ml_security/__init__.py
ml_security/logger.py
ml_security/attacks/__init__.py
ml_security/attacks/base.py
ml_security/attacks/carlini_wagner_attack.py
ml_security/attacks/fast_gradient_sign_attack.py
ml_security/attacks/membership_inference_attack.py
ml_security/attacks/projected_gradient_descent_attack.py
ml_security/datasets/__init__.py
ml_security/datasets/datasets.py
ml_security/datasets/tabular_UCI.py
ml_security/utils/__init__.py
ml_security/utils/distance.py
ml_security/utils/nlp_utils.py
ml_security/utils/utils.py
ml_security-0.0.7.dist-info/LICENSE
ml_security-0.0.7.dist-info/METADATA
ml_security-0.0.7.dist-info/WHEEL
ml_security-0.0.7.dist-info/top_level.txt
ml_security-0.0.7.dist-info/RECORD
