Metadata-Version: 2.1
Name: ml_security
Version: 0.0.7
Summary: PhD work/exploration @ FEUP, PORTO
Author: Rui Melo
Author-email: rufimelo99@gmail.com
Classifier: Programming Language :: Python :: 3
Classifier: License :: OSI Approved :: MIT License
Classifier: Operating System :: OS Independent
Requires-Python: >=3.10
License-File: LICENSE
Requires-Dist: structlog>=24.1.0
Requires-Dist: pandas>=2.2.3
Requires-Dist: numpy>=2.1.1
Requires-Dist: typing>=3.7.4.3
Requires-Dist: isort==5.13.2
Requires-Dist: black==24.8.0
Requires-Dist: torch>=2.4.1
Requires-Dist: einops>=0.8.0
Requires-Dist: tqdm==4.66.5
Requires-Dist: torchvision
Requires-Dist: matplotlib
Requires-Dist: scikit-learn
Requires-Dist: datasets
Requires-Dist: pre-commit
